nnef_tools/__init__.py
nnef_tools/convert.py
nnef_tools/execute.py
nnef_tools/generate.py
nnef_tools/gmac.py
nnef_tools/image_tensor.py
nnef_tools/quantize.py
nnef_tools/random_tensor.py
nnef_tools/visualize.py
nnef_tools/conversion/__init__.py
nnef_tools/conversion/converter.py
nnef_tools/conversion/nnef_to_onnx.py
nnef_tools/conversion/nnef_to_tf.py
nnef_tools/conversion/nnef_to_tflite.py
nnef_tools/conversion/onnx_to_nnef.py
nnef_tools/conversion/tf_to_nnef.py
nnef_tools/conversion/tflite_to_nnef.py
nnef_tools/interpreter/__init__.py
nnef_tools/interpreter/pytorch/__init__.py
nnef_tools/interpreter/pytorch/nnef_module.py
nnef_tools/interpreter/pytorch/nnef_operators.py
nnef_tools/io/__init__.py
nnef_tools/io/caffe2/__init__.py
nnef_tools/io/caffe2/reader.py
nnef_tools/io/caffe2/writer.py
nnef_tools/io/caffe2/caffe/__init__.py
nnef_tools/io/caffe2/caffe/proto/__init__.py
nnef_tools/io/caffe2/caffe/proto/caffe_pb2.py
nnef_tools/io/nnef/__init__.py
nnef_tools/io/nnef/helpers.py
nnef_tools/io/nnef/reader.py
nnef_tools/io/nnef/writer.py
nnef_tools/io/onnx/__init__.py
nnef_tools/io/onnx/reader.py
nnef_tools/io/onnx/writer.py
nnef_tools/io/tf/__init__.py
nnef_tools/io/tf/graphdef/__init__.py
nnef_tools/io/tf/graphdef/composite.py
nnef_tools/io/tf/graphdef/protobuf.py
nnef_tools/io/tf/graphdef/reader.py
nnef_tools/io/tf/graphdef/utils.py
nnef_tools/io/tf/graphdef/writer.py
nnef_tools/io/tf/lite/__init__.py
nnef_tools/io/tf/lite/helpers.py
nnef_tools/io/tf/lite/reader.py
nnef_tools/io/tf/lite/writer.py
nnef_tools/io/tf/lite/flatbuffers/AbsOptions.py
nnef_tools/io/tf/lite/flatbuffers/ActivationFunctionType.py
nnef_tools/io/tf/lite/flatbuffers/AddNOptions.py
nnef_tools/io/tf/lite/flatbuffers/AddOptions.py
nnef_tools/io/tf/lite/flatbuffers/ArgMaxOptions.py
nnef_tools/io/tf/lite/flatbuffers/ArgMinOptions.py
nnef_tools/io/tf/lite/flatbuffers/BatchMatMulOptions.py
nnef_tools/io/tf/lite/flatbuffers/BatchToSpaceNDOptions.py
nnef_tools-1.0.9.dist-info/licenses/LICENSE
nnef_tools-1.0.9.dist-info/METADATA
nnef_tools-1.0.9.dist-info/WHEEL
nnef_tools-1.0.9.dist-info/top_level.txt
nnef_tools-1.0.9.dist-info/RECORD
