Metadata-Version: 2.4
Name: nnef_tools
Version: 1.0.9
Summary: A package for managing NNEF files
Author-email: Viktor Gyenes <viktor.gyenes@aimotive.com>, Tamas Danyluk <9149812+tdanyluk@users.noreply.github.com>
Maintainer-email: Viktor Gyenes <viktor.gyenes@aimotive.com>
License: 
Project-URL: Homepage, https://www.khronos.org/nnef
Project-URL: Repository, https://github.com/KhronosGroup/NNEF-Tools
Keywords: nnef
Classifier: Intended Audience :: Developers
Classifier: License :: OSI Approved :: Apache Software License
Classifier: Programming Language :: Python :: 3
Requires-Python: >=3.7
License-File: LICENSE
Requires-Dist: future
Requires-Dist: numpy
Requires-Dist: six
Requires-Dist: typing
Requires-Dist: nnef
Provides-Extra: caffe
Requires-Dist: protobuf; extra == "caffe"
Requires-Dist: torch; extra == "caffe"
Provides-Extra: onnx
Requires-Dist: protobuf; extra == "onnx"
Requires-Dist: onnx; extra == "onnx"
Requires-Dist: onnx-simplifier; extra == "onnx"
Requires-Dist: onnxruntime; extra == "onnx"
Provides-Extra: tensorflow-lite
Requires-Dist: nnef_tools[tensorflow-protobuf]; extra == "tensorflow-lite"
Requires-Dist: flatbuffers; extra == "tensorflow-lite"
Provides-Extra: tensorflow-protobuf
Requires-Dist: tensorflow; extra == "tensorflow-protobuf"
Provides-Extra: visualization
Requires-Dist: graphviz; extra == "visualization"
Provides-Extra: full
Requires-Dist: nnef_tools[caffe,onnx,tensorflow-lite,visualization]; extra == "full"
Dynamic: license-file
